{
    "code": "200",
    "message": "Success",
    "data": {
        "open": 880.0,
        "high": 917.95,
        "low": 875.65,
        "close": 905.95,
        "pclose": 883.55,
        "volume": 283255,
        "reqDate": "2023-11",
        "feedTime": "1699026914",
        "scId": "ARI02",
        "exchangeId": "N",
        "pivotLevels": [
            {
                "key": "Classic",
                "pivotLevel": {
                    "pivotPoint": "876.08",
                    "r1": "912.17",
                    "r2": "940.78",
                    "r3": "976.87",
                    "s1": "847.47",
                    "s2": "811.38",
                    "s3": "782.77"
                }
            },
            {
                "key": "Fibonacci",
                "pivotLevel": {
                    "pivotPoint": "876.08",
                    "r1": "900.80",
                    "r2": "916.07",
                    "r3": "940.78",
                    "s1": "851.37",
                    "s2": "836.10",
                    "s3": "811.38"
                }
            },
            {
                "key": "Camarilla",
                "pivotLevel": {
                    "pivotPoint": "876.08",
                    "r1": "889.48",
                    "r2": "895.41",
                    "r3": "901.34",
                    "s1": "877.62",
                    "s2": "871.69",
                    "s3": "865.76"
                }
            }
        ],
        "sma": [
            {
                "key": "5",
                "value": "930.84",
                "indication": "Bearish"
            },
            {
                "key": "10",
                "value": "949.00",
                "indication": "Bearish"
            },
            {
                "key": "20",
                "value": "834.66",
                "indication": "Bullish"
            },
            {
                "key": "50",
                "value": null,
                "indication": null
            },
            {
                "key": "100",
                "value": null,
                "indication": null
            },
            {
                "key": "200",
                "value": null,
                "indication": null
            }
        ],
        "ema": [
            {
                "key": "5",
                "value": "922.87",
                "indication": "Bearish"
            },
            {
                "key": "10",
                "value": "912.82",
                "indication": "Bearish"
            },
            {
                "key": "20",
                "value": "871.93",
                "indication": "Bullish"
            },
            {
                "key": "50",
                "value": null,
                "indication": null
            },
            {
                "key": "100",
                "value": null,
                "indication": null
            },
            {
                "key": "200",
                "value": null,
                "indication": null
            }
        ],
        "crossover": [
            {
                "key": "5_20",
                "displayValue": "5 & 20 DMA Crossover",
                "indication": "Bullish",
                "period": "Short Term"
            },
            {
                "key": "20_50",
                "displayValue": "20 & 50 DMA Crossover",
                "indication": null,
                "period": "Medium Term"
            },
            {
                "key": "50_200",
                "displayValue": "50 & 200 DMA Crossover",
                "indication": null,
                "period": "Long Term"
            }
        ],
        "indicators": [
            {
                "id": "rsi",
                "displayName": "RSI(14)",
                "value": "56.59",
                "indication": "Bullish"
            },
            {
                "id": "macd",
                "displayName": "MACD(12,26,9)",
                "value": "38.97",
                "indication": "Bullish"
            },
            {
                "id": "stochastic",
                "displayName": "Stochastic(20,3)",
                "value": "52.27",
                "indication": "Neutral"
            },
            {
                "id": "roc",
                "displayName": "ROC(20)",
                "value": "9.89",
                "indication": "Bullish"
            },
            {
                "id": "cci",
                "displayName": "CCI(20)",
                "value": "33.28",
                "indication": "Neutral"
            },
            {
                "id": "williamsR",
                "displayName": "Williamson%R(14)",
                "value": "-49.41",
                "indication": "Bullish"
            },
            {
                "id": "mfi",
                "displayName": "MFI(14)",
                "value": "62.22",
                "indication": "Neutral"
            },
            {
                "id": "atr",
                "displayName": "ATR(14)",
                "value": "133.99",
                "indication": "Low Volatility"
            },
            {
                "id": "adx",
                "displayName": "ADX(14)",
                "value": "18.66",
                "indication": "Weak Trend"
            },
            {
                "id": "bollinger",
                "displayName": "Bollinger Band(20,2)",
                "value": [
                    {
                        "id": "upperband",
                        "displayName": "UB",
                        "value": "1155.67"
                    },
                    {
                        "id": "lowerband",
                        "displayName": "LB",
                        "value": "513.66"
                    },
                    {
                        "id": "sma20",
                        "displayName": "SMA20",
                        "value": "834.66"
                    }
                ],
                "indication": "- -"
            }
        ],
        "sentiments": {
            "movingAverageSentiment": {
                "bearishCount": 2,
                "bullishCount": 1,
                "neutralCount": 0,
                "indication": "Bearish"
            },
            "movingAverageCrossOverSentiment": {
                "bearishCount": 0,
                "bullishCount": 1,
                "neutralCount": 0,
                "indication": "- -"
            },
            "indicatorsSentiment": {
                "bearishCount": 0,
                "bullishCount": 4,
                "neutralCount": 3,
                "indication": "Bullish"
            },
            "totalBearish": 2,
            "totalBullish": 6,
            "totalNeutral": 3,
            "indication": "Bullish"
        }
    }
}